{"ChIJC0ojTgDLvJUR9lU_idENpO8": {"score": 4.3, "reviews": 85}, "ChIJdwHD6ELLvJURk1xxhtekphI": {"score": 4.5, "reviews": 3177}, "ChIJm1ElIILDG5QRcfGZXNK-824": {"score": 4.6, "reviews": 696}, "ChIJKV3IiyzLvJURkVGKnD83aK8": {"score": 4.6, "reviews": 2780}, "ChIJ5YeD_bvLvJUR0Lg4wr7ewkc": {"score": 4.8, "reviews": 4412}, "ChIJJzcrUHfLvJURUqiOezuG1wA": {"score": 4.4, "reviews": 3589}, "ChIJY9ZAUOtnt5URnUQvTONSawU": {"score": 4.7, "reviews": 1146}, "ChIJFVmGU3_LvJURq58aJcAEEGE": {"score": 4.2, "reviews": 1068}, "ChIJdabHUlbKvJUR0-vVgJbPCGk": {"score": 4.4, "reviews": 12301}, "ChIJU_DCEHW3vJURcV7hPPNFORc": {"score": 4.4, "reviews": 1930}, "ChIJRx6Z_EBV5L0RXLcGYxpnPIw": {"score": 4.4, "reviews": 447}, "ChIJf2ae6MbLvJURi0HAKnC9z3k": {"score": 4.8, "reviews": 8944}, "ChIJ_4iEQNa5vJUR5UyekmLFe9o": {"score": 4.5, "reviews": 1419}, "ChIJGboeRAC_vJURSQWOK26GkW4": {"score": 4.7, "reviews": 417}, "ChIJka4zZjC1vJURgZflcN7eYS4": {"score": 4.4, "reviews": 1955}, "ChIJESuvjIXJvJURvd0bf0gEqQo": {"score": 4.5, "reviews": 1069}, "ChIJvyFUSQC3vJUReYz9I1J3Pd4": {"score": 4.5, "reviews": 421}, "ChIJ8ZxObe6pupUR41a4i1MESZ8": {"score": 4.6, "reviews": 487}, "ChIJ9WkNSES5vJURQKpKTNcISe4": {"score": 4.7, "reviews": 3513}, "ChIJCeFoPAAPG5QRfd80k993A00": {"score": 4.5, "reviews": 712}, "ChIJEXhKGgBnt5UR_KfmmzowUSs": {"score": 4.9, "reviews": 71}, "ChIJkfe5UwDdhJURTKhewUY3_D4": {"score": 4.4, "reviews": 120}, "ChIJm6ZHeurFvJURo5TWz9SQmgI": {"score": 4.7, "reviews": 1571}, "ChIJ_464zcqxvJUR5ju5D1wHkxs": {"score": 4.6, "reviews": 3110}, "ChIJtapxJQnJvJURUpyYB1S6oeE": {"score": 4.4, "reviews": 609}, "ChIJkb5wyb6VvJUR3s6crD4OEZc": {"score": 4.6, "reviews": 338}, "ChIJDXtVgrTJvJURpaKnvv3bx94": {"score": 4.7, "reviews": 3221}, "ChIJAT-jl5nHvJURvZimS3AcemY": {"score": 4.8, "reviews": 7044}, "ChIJu1hfdwC5vJURNKFGzjqEHBU": {"score": 4.4, "reviews": 139}, "ChIJASImSQDLvJURsB6wCAbMGRw": {"score": 4.4, "reviews": 229}, "ChIJo4fxOB7LvJURwKHvoNQ3q4w": {"score": 4.0, "reviews": 218}, "ChIJSUT4UQC3vJURQUVzmMcsU6U": {"score": 4.6, "reviews": 229}, "ChIJeV00IyfLvJUR3ubt6W-U8yw": {"score": 4.4, "reviews": 285}, "ChIJ3wxYcwDLvJURcOyNGuJ-7pE": {"score": 4.7, "reviews": 95}, "ChIJS1FGYwBtRZQRpFFmWJXu678": {"score": 4.8, "reviews": 219}, "ChIJy0ubYKTJvJURx-woUNha8ks": {"score": 4.4, "reviews": 287}, "ChIJBcPMKgC5vJUR5NPIaosDj8I": {"score": 4.9, "reviews": 1213}, "ChIJi2ruko-jvJURNwlsgHBaWZU": {"score": 4.7, "reviews": 215}, "ChIJXVuDdAC1vJURqqQJQhBLWF4": {"score": 4.4, "reviews": 63}, "ChIJCe6BHy2ZvJURjfEFZ-CrZwQ": {"score": 4.6, "reviews": 67}, "ChIJOdvxEtHnopURnGEPtq35dss": {"score": 4.5, "reviews": 338}, "ChIJiQMrBwDLvJUR9wQ3QbbxX3Q": {"score": 4.3, "reviews": 71}, "ChIJ64UxYADJvJUR_yF6YcHbZ_s": {"score": 4.7, "reviews": 204}, "ChIJ99tBBAAJfpYRLmQJ5DRw80E": {"score": 4.0, "reviews": 96}, "ChIJ87bBU0vRvJURmMv3XqEk75E": {"score": 4.5, "reviews": 164}, "ChIJCZ7gNZDNvJURa4OqQcFtsas": {"score": 4.3, "reviews": 124}, "ChIJBTqpBdXLvJURbvZzwaEfMiE": {"score": 4.4, "reviews": 37}, "ChIJnTl8WNCVvJUR5dIt23pDZgA": {"score": 4.7, "reviews": 94}, "ChIJdaN2JH3HvJURAAvFrYwCtRo": {"score": 4.6, "reviews": 252}, "ChIJk3VjpI_LvJUR0vrvUfs1AF8": {"score": 4.9, "reviews": 274}, "ChIJEVSZPXoNRZQRTFJ-SpMjESE": {"score": 4.3, "reviews": 211}, "ChIJeQ2DVMa3vJUR9WwlEwPrHQU": {"score": 4.6, "reviews": 102}, "ChIJPaeoCQCdvJURX_nNMgrZa50": {"score": 4.2, "reviews": 255}, "ChIJ49FZTRzLvJUR5Xt2ZtNueSc": {"score": 4.6, "reviews": 161}, "ChIJV25xSwAvo5URss2rSU2srHc": {"score": 4.4, "reviews": 57}, "ChIJ48CqudPHvJURNZK70e8o8uE": {"score": 4.6, "reviews": 118}, "ChIJN4pDXVoNRZQRbh55N8y6uNk": {"score": 4.8, "reviews": 94}, "ChIJ-T3i8sSxvJURsG8WJkzX2qo": {"score": 4.8, "reviews": 1054}, "ChIJpQfUrT7DG5QRkBsREHiY3Vw": {"score": 4.8, "reviews": 264}, "ChIJw233JuwB0pURvnbR5KPEunE": {"score": 4.0, "reviews": 75}, "ChIJyaX773ert5URNL6dX_UMyDo": {"score": 4.6, "reviews": 168}, "ChIJSbdxwaM51JURkhhHdeFg2-A": {"score": 4.4, "reviews": 64}, "ChIJLQ0kkmm3vJURyVlFCYGzAIw": {"score": 4.8, "reviews": 342}, "ChIJ9QQTy6ulvJUR3vjyKR4-CDg": {"score": 4.7, "reviews": 122}, "ChIJv2Z03bVdIpQR6SuWgNKjcMs": {"score": 4.6, "reviews": 69}, "ChIJQdshdAC3vJUR9t9kfIyF2Sw": {"score": 4.4, "reviews": 164}, "ChIJZRkms_zHvJURZQI3bM7VLUE": {"score": 4.4, "reviews": 79}, "ChIJEbZEHgAzCpYRVs04lGArZng": {"score": 4.0, "reviews": 780}, "ChIJF5ypHhjLvJUR8znoO9iZAi4": {"score": 4.7, "reviews": 5514}, "ChIJk6cWKo7LvJURm6dkaFHdfNc": {"score": 4.6, "reviews": 1918}, "ChIJFRsKJXmhvJURCaMbu_X-hCY": {"score": 4.3, "reviews": 556}, "ChIJHXbbXYq1vJURPR5M2xosDpg": {"score": 4.3, "reviews": 3494}, "ChIJP2xHwFCxvJURy_uQI_P9XpU": {"score": 4.4, "reviews": 1319}, "ChIJiyQxjAyxvJURsr3OGZUSbcc": {"score": 4.5, "reviews": 894}, "ChIJScfoLeGlvJURfLEVKvHiARE": {"score": 4.6, "reviews": 2289}, "ChIJXTJBsfGdvJURc9MfAn2aO1A": {"score": 4.8, "reviews": 5311}, "ChIJtZgXFUnHvJURo3MkPxTXXzU": {"score": 4.7, "reviews": 2282}, "ChIJ56SpNADLC5YRWRUeCa5lhFo": {"score": 4.3, "reviews": 256}, "ChIJZaPSRlAvo5URPTWJXdLosYw": {"score": 4.2, "reviews": 419}, "ChIJL6esSQC9vJURjIQiafFCQgM": {"score": 4.8, "reviews": 543}, "ChIJcYI2vNG1vJURq0rvApiVNDs": {"score": 4.4, "reviews": 136}, "ChIJu_V9ci9lyJURaF_58K06lsQ": {"score": 4.7, "reviews": 112}, "ChIJy9-aBUW1vJURLQhHnM7YsUg": {"score": 4.5, "reviews": 65}, "ChIJz-X_ZtvLvJURJyx1mDifpU0": {"score": 4.9, "reviews": 139}, "ChIJd7urHQCjMpQRmCdyISCmyzI": {"score": 4.3, "reviews": 73}, "ChIJaepNfAC3vJURPEMb7laADXI": {"score": 4.9, "reviews": 223}, "ChIJ-ab9KQDdhJURtNoN4e2nMb4": {"score": 4.4, "reviews": 86}, "ChIJnZxCfwC_vJUR4c98fkLUroo": {"score": 4.8, "reviews": 1665}, "ChIJfWIHpXSnXZQRldNmJzgKakM": {"score": 4.4, "reviews": 274}, "ChIJnx1kxwDnopUR3qqoTMiJVwk": {"score": 4.4, "reviews": 104}, "ChIJSx6ucEkzo5URHs9HjRyM0fQ": {"score": 4.8, "reviews": 183}, "ChIJs__7AADRvJURXmbp3yaEtGA": {"score": 4.9, "reviews": 177}, "ChIJlWW0dADLvJURnHLjGWWvT34": {"score": 4.9, "reviews": 72}, "ChIJf08mFiDDG5QRBVh_NMVw7iA": {"score": 4.8, "reviews": 108}, "ChIJ0VsH74_DG5QR2LaD-dsSplE": {"score": 4.7, "reviews": 94}, "ChIJD9FvULa_V5QRAyWJmuVri0E": {"score": 4.5, "reviews": 80}, "ChIJqeWDEgC9vJURdeiLs54aepY": {"score": 5.0, "reviews": 555}, "ChIJ8XoXj6i3vJURtQnKY0yxBvA": {"score": 4.5, "reviews": 26}, "ChIJpcYFcGe1vJURi3vNL1zUWcg": {"score": 4.6, "reviews": 41}, "ChIJF89QVkfLvJUR_d6jUYDo0e4": {"score": 4.7, "reviews": 103}, "ChIJK23FdgrTvJURaK3SjMYf2Dg": {"score": 4.5, "reviews": 38}, "ChIJvxnFvhdJIpQRKEhs4agwioY": {"score": 5.0, "reviews": 38}, "ChIJmR9cDQCfvJURb4hz0a_MWlA": {"score": 4.6, "reviews": 44}, "ChIJG1VHyQ_LvJURN3FlweNfuzc": {"score": 4.7, "reviews": 54}, "ChIJLa-Q5Cq9vJUR15Ctvm6cbcE": {"score": 4.9, "reviews": 103}, "ChIJN08Y_DO1uZUReB2rDKnOosU": {"score": 4.7, "reviews": 43}, "ChIJ76siuw9dIpQRiSjK1vUh0nQ": {"score": 4.8, "reviews": 150}, "ChIJcaMdrxS3vJURFE_r2COESy8": {"score": 4.8, "reviews": 159}, "ChIJIeZ1UG23vJURedyjmoRfFno": {"score": 4.6, "reviews": 56}}